<memory offset="0x8015BC70" value="48000000" />
<memory offset="0x809246E0" value="48000000" />
<memory offset="0x80102238" value="48000001" />
<memory offset="0x8091F930" value="48000000" />
<memory offset="0x80920124" value="48000001" />
<memory offset="0x8092016C" value="48000001" />
<memory offset="0x8091F6E8" value="48000000" />
<memory offset="0x800951EC" value="48000001" />
<memory offset="0x8008C3E0" value="48000000" />
<memory offset="0x80065620" value="48000000" />
<memory offset="0x80095730" value="48000000" />
<memory offset="0x800A08F0" value="48000001" />
<memory offset="0x800A0A50" value="48000001" />
<memory offset="0x800DB690" value="48000000" />
<memory offset="0x800DB6B4" value="48000000" />
<memory offset="0x800DB6E8" value="48000000" />
<memory offset="0x800DB6FC" value="48000000" />
<memory offset="0x80ABB6D0" value="48000001" />
<memory offset="0x80ABB758" value="48000001" />
<memory offset="0x80A5AAA8" value="48000001" />
<memory offset="0x80A5AAC4" value="48000001" />
<memory offset="0x80A5AB44" value="48000001" />
<memory offset="0x80A5AB80" value="48000001" />
<memory offset="0x80A5AB9C" value="48000001" />
<memory offset="0x80A5ABB8" value="48000001" />
<memory offset="0x80A6A208" value="48000001" />
<memory offset="0x80A6A22C" value="48000001" />
<memory offset="0x80A6A2A8" value="48000001" />
<memory offset="0x80A6A2CC" value="48000001" />
<memory offset="0x802EE81C" value="41c00000" />
<memory offset="0x800980A4" value="48000001" />
<memory offset="0x80A9ED2C" value="48000001" />
<memory offset="0x80A9EE58" value="48000001" />
<memory offset="0x800A18E8" value="48000001" />
<memory offset="0x807FAAAC" value="48000000" />
<memory offset="0x807FA9C0" value="48000001" />
<memory offset="0x8042C6BC" value="45abe000" />
<memory offset="0x80AAEAAC" value="48000001" />
<memory offset="0x8010D014" value="48000001" />
<memory offset="0x80234CE0" value="48000001" />
<memory offset="0x8034D410" value="00000000" />
<memory offset="0x8034D590" value="00000000" />
<memory offset="0x8034D5B8" value="00000000" />
<memory offset="0x8034D614" value="00000000" />
<memory offset="0x8034D634" value="00000000" />
<memory offset="0x8034D770" value="00000000" />
<memory offset="0x80A93038" value="48000000" />
<memory offset="0x809CB118" value="2c1c0003" />
<memory offset="0x8008E6F8" value="38600000" />
<memory offset="0x8015D850" value="38600000" />
<memory offset="0x80781FB8" value="60000000" />
<memory offset="0x800E53E0" value="4e800020" />
<memory offset="0x80132EFC" value="48000001" />
<memory offset="0x80133120" value="48000001" />
<memory offset="0x80133134" value="48000001" />
<memory offset="0x80133148" value="48000001" />
<memory offset="0x80132AE8" value="48000001" />
<memory offset="0x801334E4" value="48000001" />
<memory offset="0x8008E5E4" value="48000000" />
<memory offset="0x802F6BC8" value="00000000000000000000000000000000" />
<memory offset="0x802F6BE0" value="0000000000000000" />
<memory offset="0x802F6C10" value="0000000000000000" />
<memory offset="0x802F6CB0" value="00000000000000000000000000000000" />
<memory offset="0x802F6CC8" value="0000000000000000" />
<memory offset="0x802F6CF8" value="0000000000000000" />
<memory offset="0x807EBC5C" value="48000000" />
<memory offset="0x801180AC" value="38000003" />
<memory offset="0x800508F8" value="a01e0010540007ff41820014a0e300043807fffeb01f042c4800000c38000001b01f042ca0a30002a89f042c80c6003c7c052214540020367ca60214a8850002" />
<memory offset="0x80050A5C" value="88030013" />
<memory offset="0x80050A60" value="2c000000" />
<memory offset="0x80050A68" value="2c000001" />
<memory offset="0x80050A70" value="2c000002" />
<memory offset="0x80050A78" value="2c000003" />
<memory offset="0x80050A88" value="389f065c" />
<memory offset="0x8030A4D0" value="00c8000000000008fffffff000000000000000000000000a0000000a000000000000000000020000" />
<memory offset="0x807E16D0" value="88d2038f" />
<memory offset="0x8001F93C" value="48000014" />
<memory offset="0x808A9448" value="60000000" />
<memory offset="0x80892DFC" value="48000000" />
<memory offset="0x80893044" value="48000000" />
<memory offset="0x800E596C" value="48000000" />
<memory offset="0x8006A6C4" value="48000000" />
<memory offset="0x80ACF6A0" value="45abe000" />
<memory offset="0x809B6EF0" value="38600000" />
<memory offset="0x809B6EC0" value="38600000" />
<memory offset="0x809B6EB0" value="38600000" />
<memory offset="0x8011857C" value="48000000" />
<memory offset="0x8011A82C" value="48000000" />
<memory offset="0x809B6F60" value="48000000" />
<memory offset="0x808399D4" value="48000001" />
<memory offset="0x80839B00" value="48000000" />
<memory offset="0x809F5E44" value="48000000" />
<memory offset="0x809F5E40" value="60000000" />
<memory offset="0x809EB284" value="60000000" />
<memory offset="0x809EC5B4" value="38600001" />
<memory offset="0x80816370" value="48000001" />
<memory offset="0x801465DC" value="48000001" />
<memory offset="0x800E3AB8" value="48000001" />
<memory offset="0x8030DA24" value="00000000ffffffc00000001000000040004000400000000000000000" />
<memory offset="0x809259E0" value="48000000" />
<memory offset="0x808AC778" value="38600400" />
<memory offset="0x80926200" value="48000000" />
<memory offset="0x8007EA98" value="48000000" />
<memory offset="0x8007EA60" value="48000000" />
<memory offset="0x80898798" value="38600400" />
<memory offset="0x807E15D0" value="48000000" />
<memory offset="0x80083490" value="48000000" />
<memory offset="0x8001DFDC" value="60000000" />
<memory offset="0x8001E02C" value="60000000" />
<memory offset="0x80142650" value="48000000" />
<memory offset="0x800B1A50" value="48000000" />
<memory offset="0x80132670" value="48000000" />
<memory offset="0x80141F70" value="48000000" />
<memory offset="0x801466C0" value="48000000" />
<memory offset="0x801421AC" value="48000001" />
<memory offset="0x8014676C" value="48000001" />
<memory offset="0x80133E48" value="48000001" />
<memory offset="0x80138840" value="48000001" />
<memory offset="0x807FCBA8" value="3860045c" />
<memory offset="0x8013BEE4" value="48000000" />
<memory offset="0x8013C3A0" value="48000000" />
<memory offset="0x8013BB7C" value="4181003c" />
<memory offset="0x8013BBB8" value="48000000" />
<memory offset="0x802EE628" value="00000006" />
<memory offset="0x802EE664" value="000000aa" />
<memory offset="0x802EE6AC" value="000000aa" />
<memory offset="0x80022884" value="281f00aa" />
<memory offset="0x80022B88" value="280500aa" />
<memory offset="0x800221AC" value="28000003" />
<memory offset="0x80A2BE98" value="28000003" />
<memory offset="0x80A28598" value="28000003" />
<memory offset="0x800611C4" value="60000000" />
<memory offset="0x8006122C" value="60000000" />
<memory offset="0x802F5AEC" value="00000001" />
<memory offset="0x8095CDD4" value="68616d6d65724d00" />
<memory offset="0x800CA658" value="48000000" />
<memory offset="0x8091EC74" value="48000000" />
<memory offset="0x8091EC6C" value="38c00028" />
<memory offset="0x80A285FC" value="48000001" />
<memory offset="0x80A27CE4" value="48000001" />
<memory offset="0x80A2C0B4" value="48000000" />
<memory offset="0x800D47D4" value="48000000" />
<memory offset="0x80141334" value="48000000" />
<memory offset="0x80141510" value="48000000" />
<memory offset="0x800CA6F8" value="48000000" />
<memory offset="0x800BCFB0" value="48000000" />
<memory offset="0x800D6FDC" value="48000001" />
<memory offset="0x8004CC80" value="48000001" />
<memory offset="0x800D7064" value="48000001" />
<memory offset="0x801293D0" value="48000001" />
<memory offset="0x80137CDC" value="48000001" />
<memory offset="0x80141FF4" value="48000000" />
<memory offset="0x8014378C" value="48000001" />
<memory offset="0x80143884" value="48000001" />
<memory offset="0x80ACE8E4" value="0008820c" />
<memory offset="0x80ACF9D0" value="0008820e" />
<memory offset="0x80ACF9F4" value="0008820e" />
<memory offset="0x80AD4AA0" value="0008a80e" />
<memory offset="0x80AD4AA4" value="20020000" />
<memory offset="0x80ACE17C" value="00080a04" />
<memory offset="0x80AD4D88" value="00080006" />
<memory offset="0x80ACDD50" value="00080006" />
<memory offset="0x80AD4F48" value="00088a1e" />
<memory offset="0x80AD5214" value="00088206" />
<memory offset="0x80ACFBC4" value="00088206" />
<memory offset="0x80AD2748" value="0008881e" />
<memory offset="0x80ACD988" value="0008a2be" />
<memory offset="0x80AD3C60" value="00088a0e" />
<memory offset="0x80AD3C3C" value="00088a0e" />
<memory offset="0x80ACEC60" value="00088a0e" />
<memory offset="0x80ACECF8" value="0008828e" />
<memory offset="0x80ACED1C" value="0008828e" />
<memory offset="0x80AD4158" value="0008a80e" />
<memory offset="0x80AD5538" value="003afffe" />
<memory offset="0x80ACD9A0" value="0008a2be" />
<memory offset="0x80ACDC8C" value="0000004f" />
<memory offset="0x80ACDC90" value="ffbaffbc" />
<memory offset="0x80AD2618" value="0000004f" />
<memory offset="0x80AD261C" value="00088806" />
<memory offset="0x80AD22B8" value="03000000" />
<memory offset="0x80AD22DC" value="03000000" />
<memory offset="0x80AD3ADC" value="00000047" />
<memory offset="0x80AD3B00" value="00000047" />
<memory offset="0x807F9694" value="48000000" />
<memory offset="0x8095C668" value="00000010" />
<memory offset="0x80AD0EB4" value="0000004f" />
<memory offset="0x80AD0ED8" value="0000004f" />
<memory offset="0x80ACFD08" value="0000004f" />
<memory offset="0x80ACFD2C" value="0000004f" />
<memory offset="0x801443C8" value="38602d0c" />
<memory offset="0x801447D4" value="48000000" />
<memory offset="0x8014516C" value="48000000" />
<memory offset="0x80145BE0" value="48000000" />
<memory offset="0x808C5108" value="38600388" />
<memory offset="0x808C52A0" value="48000000" />
<memory offset="0x808C5A30" value="48000000" />
<memory offset="0x808C5910" value="48000000" />
<memory offset="0x8030D5B4" value="00020000" />
<memory offset="0x80124DDC" value="28001234" />
<memory offset="0x80102370" value="48000000" />
<memory offset="0x80427C04" value="000003e7" />
<memory offset="0x8030AF48" value="0149000000000008fffffff00000000000000010000000ff00000010000000000000000000000000" />
<memory offset="0x8081BF10" value="48000000" />
<memory offset="0x8081BF20" value="48000000" />
<memory offset="0x8030E418" value="0147000000000008fffffff00000000000000010000000ff00000010000000000000000000000000" />
<memory offset="0x8030B560" value="00a2000000000008fffffff0000000000000001000000fff00000fff000000000000000000000000" />
